{
  "file": "r4-concurrent-fetch.cpp",
  "conciseness": {
    "loc": 32,
    "tokens": 92,
    "chars": 723,
    "halsteadVolume": 543,
    "compressionRatio": 0.436,
    "tokensPerLine": 2.88
  },
  "sigils": {
    "sigilsPerLine": 6.53,
    "uniqueSigilTypes": 18,
    "totalSigils": 209
  },
  "readability": {
    "avgLineLength": 31,
    "maxNesting": 13,
    "avgIdentifierLength": 4.7,
    "visualDensity": 0.701
  },
  "concepts": {
    "keywords": 8,
    "syntaxPatterns": 3,
    "apiCalls": 5,
    "conceptCount": 11
  },
  "guardrails": {
    "memory": 0.5,
    "null": 0.5,
    "race": 0,
    "overflow": 0,
    "coercion": 0,
    "guardrailScore": 1.7
  },
  "ceremony": {
    "ceremonyLines": 11,
    "ceremonyRatio": 0.344
  },
  "surfaceArea": {
    "keywords": 92,
    "concepts": 135
  }
}
