{
  "file": "s1-channel-pipeline.py",
  "conciseness": {
    "loc": 18,
    "tokens": 56,
    "chars": 368,
    "halsteadVolume": 306,
    "compressionRatio": 0.498,
    "tokensPerLine": 3.11
  },
  "sigils": {
    "sigilsPerLine": 4.39,
    "uniqueSigilTypes": 7,
    "totalSigils": 79
  },
  "readability": {
    "avgLineLength": 26,
    "maxNesting": 3,
    "avgIdentifierLength": 4,
    "visualDensity": 0.768
  },
  "concepts": {
    "keywords": 9,
    "syntaxPatterns": 2,
    "apiCalls": 7,
    "conceptCount": 11
  },
  "guardrails": {
    "memory": 1,
    "null": 0.67,
    "race": 0,
    "overflow": 1,
    "coercion": 0.67,
    "guardrailScore": 3.8,
    "grMemoryWhen": "compile",
    "grMemoryActivation": "default",
    "grNullWhen": "runtime",
    "grNullActivation": "default",
    "grRaceWhen": "none",
    "grRaceActivation": "default",
    "grOverflowWhen": "compile",
    "grOverflowActivation": "default",
    "grCoercionWhen": "runtime",
    "grCoercionActivation": "default"
  },
  "ceremony": {
    "ceremonyLines": 2,
    "ceremonyRatio": 0.111
  },
  "surfaceArea": {
    "keywords": 39,
    "concepts": 75,
    "categories": {
      "types": 8,
      "controlFlow": 10,
      "functions": 10,
      "oopData": 18,
      "memory": 2,
      "concurrency": 10,
      "metaprogramming": 12,
      "errorHandling": 5
    },
    "keywordRatio": 0.52
  }
}
